{
  "_class": "group",
  "do_objectID": "962FF453-264F-44D0-9D16-B5A5CC9C4BDE",
  "exportOptions": {
    "_class": "exportOptions",
    "exportFormats": [
    ],
    "includedLayerIds": [
    ],
    "layerOptions": 0,
    "shouldTrim": false
  },
  "frame": {
    "_class": "rect",
    "constrainProportions": false,
    "height": 56,
    "width": 280,
    "x": 0,
    "y": 112
  },
  "hasClickThrough": false,
  "isFlippedHorizontal": false,
  "isFlippedVertical": false,
  "isLocked": false,
  "isVisible": true,
  "layerListExpandedType": 0,
  "layers": [
    {
      "class": "shapeGroup",
      "id": "13989D55-7172-4C92-9957-B1150937939F"
    },
    {
      "class": "text",
      "id": "E3645464-7AE3-426C-9192-33E62E41F8C5"
    },
    {
      "class": "symbolInstance",
      "id": "595A3850-3841-4077-9EA6-30B7921AB5B4"
    }
  ],
  "name": "row copy 3",
  "nameIsFixed": true,
  "resizingConstraint": 63,
  "resizingType": 0,
  "rotation": 0,
  "shouldBreakMaskChain": false,
  "style": {
    "_class": "style",
    "endDecorationType": 0,
    "miterLimit": 10,
    "startDecorationType": 0
  },
  "userInfo": {
    "com.animaapp.stc-sketch-plugin": {
      "kModelPropertiesKey": {
      }
    }
  }
}