{
  "_class": "shapeGroup",
  "clippingMaskMode": 0,
  "do_objectID": "DE35229B-AAF6-4427-A13A-33399977C0ED",
  "exportOptions": {
    "_class": "exportOptions",
    "exportFormats": [
    ],
    "includedLayerIds": [
    ],
    "layerOptions": 0,
    "shouldTrim": false
  },
  "frame": {
    "_class": "rect",
    "constrainProportions": false,
    "height": 18,
    "width": 24,
    "x": 312,
    "y": 129
  },
  "hasClickThrough": false,
  "hasClippingMask": false,
  "isFlippedHorizontal": false,
  "isFlippedVertical": false,
  "isLocked": false,
  "isVisible": true,
  "layerListExpandedType": 0,
  "layers": [
    {
      "class": "shapePath",
      "id": "821DA412-89A6-40F4-9ACB-CEA76225AEE5"
    },
    {
      "class": "shapePath",
      "id": "1EC403B3-0D30-46F3-A460-15695F896C68"
    }
  ],
  "name": "delete 2",
  "nameIsFixed": true,
  "originalObjectID": "DE35229B-AAF6-4427-A13A-33399977C0ED",
  "resizingConstraint": 63,
  "resizingType": 0,
  "rotation": 0,
  "shouldBreakMaskChain": false,
  "style": {
    "_class": "style",
    "contextSettings": {
      "_class": "graphicsContextSettings",
      "blendMode": 0,
      "opacity": 0.6
    },
    "endDecorationType": 0,
    "fills": [
      {
        "_class": "fill",
        "color": {
          "_class": "color",
          "alpha": 1,
          "blue": 0.3098039215686275,
          "green": 0.2784313725490196,
          "red": 0.2156862745098039
        },
        "fillType": 0,
        "isEnabled": true,
        "noiseIndex": 0,
        "noiseIntensity": 0,
        "patternFillType": 0,
        "patternTileScale": 1
      }
    ],
    "miterLimit": 10,
    "startDecorationType": 0
  },
  "windingRule": 1
}