{
  "_class": "shapeGroup",
  "clippingMaskMode": 0,
  "do_objectID": "46371A79-21DD-425A-A111-4D6436504359",
  "exportOptions": {
    "_class": "exportOptions",
    "exportFormats": [
    ],
    "includedLayerIds": [
    ],
    "layerOptions": 0,
    "shouldTrim": false
  },
  "frame": {
    "_class": "rect",
    "constrainProportions": false,
    "height": 10.69933980582524,
    "width": 7.763417475728161,
    "x": 99.09227184466019,
    "y": 9.190974757281555
  },
  "hasClickThrough": false,
  "hasClippingMask": false,
  "isFlippedHorizontal": false,
  "isFlippedVertical": false,
  "isLocked": false,
  "isVisible": true,
  "layerListExpandedType": 1,
  "layers": [
    {
      "class": "shapePath",
      "id": "724D0A9E-9D1C-4953-89A3-84BD140DDDE0"
    }
  ],
  "name": "Fill 50",
  "nameIsFixed": false,
  "originalObjectID": "46371A79-21DD-425A-A111-4D6436504359",
  "resizingConstraint": 63,
  "resizingType": 0,
  "rotation": 0,
  "shouldBreakMaskChain": false,
  "style": {
    "_class": "style",
    "endDecorationType": 0,
    "fills": [
      {
        "_class": "fill",
        "color": {
          "_class": "color",
          "alpha": 1,
          "blue": 0.1252310872077942,
          "green": 0.1220022812485695,
          "red": 0.1366096138954163
        },
        "fillType": 0,
        "isEnabled": true,
        "noiseIndex": 0,
        "noiseIntensity": 0,
        "patternFillType": 1,
        "patternTileScale": 1
      }
    ],
    "miterLimit": 10,
    "startDecorationType": 0
  },
  "windingRule": 1
}